{
    "nodeConfig": {
        "tag": "GraphNodeConfig",
        "graphServiceConfig": {
            "dbConfig": {
                "stopOnDatabaseError": true,
                "tag": "DBConfig",
                "dbOptions": {
                    "errorIfExists": true,
                    "createIfMissing": true
                },
                "dbModelName": "",
                "useDatabase": false,
                "useEnqHomeDir": false
            },
            "tag": "GraphServiceConfig",
            "rpcSynco": null
        },
        "bnAddress": {
            "tag": "NodeAddress",
            "nodePorts": {
                "tag": "NodePorts",
                "nodeRpcPort": 6000,
                "nodeUdpPort": 4000,
                "nodeTcpPort": 5000
            },
            "nodeId": {
                "bytes": [
                    107,
                    82,
                    50,
                    47,
                    80,
                    105,
                    100,
                    114,
                    73,
                    77,
                    102,
                    115,
                    73,
                    54,
                    117,
                    54,
                    87,
                    90,
                    118,
                    121,
                    120,
                    51,
                    74,
                    79,
                    119,
                    82,
                    79,
                    108,
                    87,
                    43,
                    122,
                    55,
                    87,
                    71,
                    43,
                    107,
                    50,
                    81,
                    79,
                    43,
                    115,
                    68,
                    81,
                    61
                ]
            },
            "nodeHost": "127.0.0.1"
        },
        "nodePorts": {
            "tag": "NodePorts",
            "nodeRpcPort": 6052,
            "nodeUdpPort": 4052,
            "nodeTcpPort": 5052
        }
    },
    "node": "GraphNode",
    "loggerConfig": {
        "logFilePath": "",
        "format": "$prio $loggername: $msg",
        "logToFile": false,
        "logToConsole": true,
        "level": "Debug"
    },
    "nodeScenario": "GN"
}
